{
  "parent": "minecraft:recipes/root",
  "criteria": {
    "has_fungal_slab_light_gray": {
      "conditions": {
        "items": [
          {
            "items": "entstupidstuff:fungal_slab_light_gray"
          }
        ]
      },
      "trigger": "minecraft:inventory_changed"
    },
    "has_the_recipe": {
      "conditions": {
        "recipe": "entstupidstuff:fungal_mosaic_light_gray"
      },
      "trigger": "minecraft:recipe_unlocked"
    }
  },
  "requirements": [
    [
      "has_the_recipe",
      "has_fungal_slab_light_gray"
    ]
  ],
  "rewards": {
    "recipes": [
      "entstupidstuff:fungal_mosaic_light_gray"
    ]
  }
}